douyin_mcp_server1/__init__.py
douyin_mcp_server1/__main__.py
douyin_mcp_server1/extract_local_video.py
douyin_mcp_server1/mcp_server.py
douyin_mcp_server1/minimal_server.py
douyin_mcp_server1/processor.py
douyin_mcp_server1/server.py
douyin_mcp_server1/server_fastmcp.py
douyin_mcp_server1/server_fastmcp_real.py
douyin_mcp_server1/server_final.py
douyin_mcp_server1/server_original.py
douyin_mcp_server1/server_original_compatible.py
douyin_mcp_server1/tools.py
douyin_mcp_server1-1.5.5.dist-info/METADATA
douyin_mcp_server1-1.5.5.dist-info/WHEEL
douyin_mcp_server1-1.5.5.dist-info/entry_points.txt
douyin_mcp_server1-1.5.5.dist-info/licenses/LICENSE
douyin_mcp_server1-1.5.5.dist-info/RECORD
