Metadata-Version: 2.4
Name: douyin-mcp-server1
Version: 1.5.5
Summary: MCP server for downloading Douyin videos and extracting text
Project-URL: Homepage, https://github.com/yzfly/douyin-mcp-server
Project-URL: Repository, https://github.com/yzfly/douyin-mcp-server
Project-URL: Issues, https://github.com/yzfly/douyin-mcp-server/issues
Author-email: yzfly <yz.liu.me@gmail.com>
License: MIT
License-File: LICENSE
Classifier: Development Status :: 3 - Alpha
Classifier: Intended Audience :: Developers
Classifier: License :: OSI Approved :: MIT License
Classifier: Programming Language :: Python :: 3
Classifier: Programming Language :: Python :: 3.10
Classifier: Programming Language :: Python :: 3.11
Classifier: Programming Language :: Python :: 3.12
Requires-Python: >=3.10
Requires-Dist: dashscope>=1.17.0
Requires-Dist: fastmcp>=2.0.0
Requires-Dist: ffmpeg-python>=0.2.0
Requires-Dist: requests>=2.25.0
Provides-Extra: full
Requires-Dist: dashscope; extra == 'full'
Requires-Dist: ffmpeg-python; extra == 'full'
Requires-Dist: tqdm; extra == 'full'
